samalg/__init__.py
samalg/_logging.py
samalg/exceptions.py
samalg/py.typed
samalg/sam.py
samalg/utilities.py
sc_sam-2.0.2.dist-info/METADATA
sc_sam-2.0.2.dist-info/WHEEL
sc_sam-2.0.2.dist-info/licenses/LICENSE.txt
sc_sam-2.0.2.dist-info/RECORD
