Metadata-Version: 2.4
Name: sc-sam
Version: 2.0.2
Summary: The Self-Assembling-Manifold algorithm for single-cell RNA sequencing analysis
Project-URL: Homepage, https://github.com/atarashansky/self-assembling-manifold
Project-URL: Documentation, https://github.com/atarashansky/self-assembling-manifold#readme
Project-URL: Repository, https://github.com/atarashansky/self-assembling-manifold
Project-URL: Issues, https://github.com/atarashansky/self-assembling-manifold/issues
Author-email: "Alexander J. Tarashansky" <tarashan@stanford.edu>
License-Expression: MIT
License-File: LICENSE.txt
Keywords: analysis,manifold,reconstruction,scrnaseq,single-cell
Classifier: Development Status :: 4 - Beta
Classifier: Intended Audience :: Science/Research
Classifier: License :: OSI Approved :: MIT License
Classifier: Operating System :: OS Independent
Classifier: Programming Language :: Python :: 3
Classifier: Programming Language :: Python :: 3.11
Classifier: Programming Language :: Python :: 3.12
Classifier: Topic :: Scientific/Engineering :: Bio-Informatics
Requires-Python: >=3.11
Requires-Dist: anndata>=0.10.0
Requires-Dist: dill>=0.3.7
Requires-Dist: h5py>=3.10.0
Requires-Dist: hnswlib>=0.8.0
Requires-Dist: numba>=0.59.0
Requires-Dist: numpy>=1.26.0
Requires-Dist: packaging>=23.0
Requires-Dist: pandas>=2.0.0
Requires-Dist: scikit-learn>=1.3.0
Requires-Dist: scipy>=1.11.0
Requires-Dist: umap-learn>=0.5.0
Provides-Extra: all
Requires-Dist: harmonypy>=0.0.5; extra == 'all'
Requires-Dist: hdbscan>=0.8.33; extra == 'all'
Requires-Dist: leidenalg>=0.10.0; extra == 'all'
Requires-Dist: louvain>=0.8.0; extra == 'all'
Requires-Dist: matplotlib>=3.8; extra == 'all'
Requires-Dist: mypy>=1.8; extra == 'all'
Requires-Dist: pre-commit>=3.6; extra == 'all'
Requires-Dist: pytest-cov>=4.1; extra == 'all'
Requires-Dist: pytest>=8.0; extra == 'all'
Requires-Dist: python-igraph>=0.11.0; extra == 'all'
Requires-Dist: ruff>=0.2; extra == 'all'
Requires-Dist: scanpy>=1.10.0; extra == 'all'
Provides-Extra: clustering
Requires-Dist: leidenalg>=0.10.0; extra == 'clustering'
Requires-Dist: louvain>=0.8.0; extra == 'clustering'
Requires-Dist: python-igraph>=0.11.0; extra == 'clustering'
Provides-Extra: dev
Requires-Dist: mypy>=1.8; extra == 'dev'
Requires-Dist: pre-commit>=3.6; extra == 'dev'
Requires-Dist: pytest-cov>=4.1; extra == 'dev'
Requires-Dist: pytest>=8.0; extra == 'dev'
Requires-Dist: ruff>=0.2; extra == 'dev'
Provides-Extra: harmony
Requires-Dist: harmonypy>=0.0.5; extra == 'harmony'
Provides-Extra: hdbscan
Requires-Dist: hdbscan>=0.8.33; extra == 'hdbscan'
Provides-Extra: viz
Requires-Dist: matplotlib>=3.8; extra == 'viz'
Requires-Dist: scanpy>=1.10.0; extra == 'viz'
